streamlit_annotation_tools/__init__.py
streamlit_annotation_tools/frontend/.env
streamlit_annotation_tools/frontend/.prettierrc
streamlit_annotation_tools/frontend/build/asset-manifest.json
streamlit_annotation_tools/frontend/build/index.html
streamlit_annotation_tools/frontend/build/static/css/main.53b583f1.css
streamlit_annotation_tools/frontend/build/static/css/main.53b583f1.css.map
streamlit_annotation_tools/frontend/build/static/js/main.cb94a59b.js
streamlit_annotation_tools/frontend/build/static/js/main.cb94a59b.js.LICENSE.txt
streamlit_annotation_tools/frontend/build/static/js/main.cb94a59b.js.map
streamlit_annotation_tools/frontend/package.json
streamlit_annotation_tools/frontend/public/index.html
streamlit_annotation_tools/frontend/src/components/Builder.tsx
streamlit_annotation_tools/frontend/src/components/Highlighter.tsx
streamlit_annotation_tools/frontend/src/components/Labeler.tsx
streamlit_annotation_tools/frontend/src/helpers/highlightHelpers.ts
streamlit_annotation_tools/frontend/src/helpers/labelerHelpers.ts
streamlit_annotation_tools/frontend/src/index.css
streamlit_annotation_tools/frontend/src/index.tsx
streamlit_annotation_tools/frontend/src/react-app-env.d.ts
streamlit_annotation_tools/frontend/src/reducers/highlightReducer.tsx
streamlit_annotation_tools/frontend/src/reducers/labelerReducer.tsx
streamlit_annotation_tools/frontend/src/types/highlightTypes.ts
streamlit_annotation_tools/frontend/src/types/labelerTypes.ts
streamlit_annotation_tools/frontend/src/utils/StreamlitProvider.tsx
streamlit_annotation_tools/frontend/src/utils/useNullableRenderData.ts
streamlit_annotation_tools/frontend/tailwind.config.js
streamlit_annotation_tools/frontend/tsconfig.json
streamlit_annotation_tools-1.0.1.dist-info/LICENSE
streamlit_annotation_tools-1.0.1.dist-info/METADATA
streamlit_annotation_tools-1.0.1.dist-info/WHEEL
streamlit_annotation_tools-1.0.1.dist-info/RECORD
